LICENSE
README.md
setup.py
AnnotatedTree/ChunkType.py
AnnotatedTree/LayerInfo.py
AnnotatedTree/ParallelTreeBankDrawable.py
AnnotatedTree/ParseNodeDrawable.py
AnnotatedTree/ParseTreeDrawable.py
AnnotatedTree/SearchType.py
AnnotatedTree/TreeBankDrawable.py
AnnotatedTree/__init__.py
AnnotatedTree/Layer/DependencyLayer.py
AnnotatedTree/Layer/EnglishPropbankLayer.py
AnnotatedTree/Layer/EnglishSemanticLayer.py
AnnotatedTree/Layer/EnglishWordLayer.py
AnnotatedTree/Layer/MetaMorphemeLayer.py
AnnotatedTree/Layer/MetaMorphemesMovedLayer.py
AnnotatedTree/Layer/MorphologicalAnalysisLayer.py
AnnotatedTree/Layer/MultiWordLayer.py
AnnotatedTree/Layer/MultiWordMultiItemLayer.py
AnnotatedTree/Layer/NERLayer.py
AnnotatedTree/Layer/PersianWordLayer.py
AnnotatedTree/Layer/ShallowParseLayer.py
AnnotatedTree/Layer/SingleWordLayer.py
AnnotatedTree/Layer/SingleWordMultiItemLayer.py
AnnotatedTree/Layer/SourceLanguageWordLayer.py
AnnotatedTree/Layer/TargetLanguageWordLayer.py
AnnotatedTree/Layer/TurkishPropbankLayer.py
AnnotatedTree/Layer/TurkishSemanticLayer.py
AnnotatedTree/Layer/TurkishWordLayer.py
AnnotatedTree/Layer/WordLayer.py
AnnotatedTree/Layer/__init__.py
AnnotatedTree/Processor/NodeDrawableCollector.py
AnnotatedTree/Processor/TreeModifier.py
AnnotatedTree/Processor/TreeToStringConverter.py
AnnotatedTree/Processor/__init__.py
AnnotatedTree/Processor/Condition/IsEnglishLeafNode.py
AnnotatedTree/Processor/Condition/IsLeafNode.py
AnnotatedTree/Processor/Condition/IsNodeWithPredicate.py
AnnotatedTree/Processor/Condition/IsNodeWithSymbol.py
AnnotatedTree/Processor/Condition/IsNodeWithSynSetId.py
AnnotatedTree/Processor/Condition/IsNoneNode.py
AnnotatedTree/Processor/Condition/IsNullElement.py
AnnotatedTree/Processor/Condition/IsNumber.py
AnnotatedTree/Processor/Condition/IsPredicateVerbNode.py
AnnotatedTree/Processor/Condition/IsProperNoun.py
AnnotatedTree/Processor/Condition/IsPunctuationNode.py
AnnotatedTree/Processor/Condition/IsTransferable.py
NlpToolkit_AnnotatedTree.egg-info/PKG-INFO
NlpToolkit_AnnotatedTree.egg-info/SOURCES.txt
NlpToolkit_AnnotatedTree.egg-info/dependency_links.txt
NlpToolkit_AnnotatedTree.egg-info/requires.txt
NlpToolkit_AnnotatedTree.egg-info/top_level.txt