Metadata-Version: 2.1
Name: NlpToolkit-AnnotatedTree
Version: 1.0.21
Summary: Annotated constituency treebank library
Home-page: https://github.com/StarlangSoftware/AnnotatedTree-Py
Author: olcaytaner
Author-email: olcaytaner@isikun.edu.tr
License: UNKNOWN
Platform: UNKNOWN
License-File: LICENSE
